README.md
setup.py
osuapi/__init__.py
osuapi/connectors.py
osuapi/dictmodel.py
osuapi/endpoints.py
osuapi/enums.py
osuapi/errors.py
osuapi/flags.py
osuapi/model.py
osuapi/osu.py
osuapi.egg-info/PKG-INFO
osuapi.egg-info/SOURCES.txt
osuapi.egg-info/dependency_links.txt
osuapi.egg-info/top_level.txt