Metadata-Version: 1.1
Name: osuapi
Version: 0.0.39
Summary: osu! api wrapper.
Home-page: https://github.com/khazhyk/osuapi
Author: khazhyk
Author-email: UNKNOWN
License: MIT
Keywords: osu
Platform: UNKNOWN
Classifier: Development Status :: 1 - Planning
Classifier: Intended Audience :: Developers
Classifier: License :: OSI Approved :: MIT License
Classifier: Topic :: Utilities
